mendeleev/__init__.py
mendeleev/ciaawparser.py
mendeleev/cli.py
mendeleev/db.py
mendeleev/econf.py
mendeleev/electronegativity.py
mendeleev/elements.db
mendeleev/fetch.py
mendeleev/interfaces/nist_asd.py
mendeleev/interfaces/wiki_oxidation_states.py
mendeleev/ion.py
mendeleev/mendeleev.py
mendeleev/models.py
mendeleev/utils.py
mendeleev/vis/__init__.py
mendeleev/vis/bokeh.py
mendeleev/vis/periodictable.py
mendeleev/vis/plotly.py
mendeleev/vis/seaborn.py
mendeleev/vis/utils.py
mendeleev-1.0.0.dist-info/AUTHORS.rst
mendeleev-1.0.0.dist-info/LICENSE
mendeleev-1.0.0.dist-info/METADATA
mendeleev-1.0.0.dist-info/WHEEL
mendeleev-1.0.0.dist-info/RECORD
