Metadata-Version: 2.3
Name: mendeleev
Version: 1.0.0
Summary: Pythonic periodic table of elements
License: MIT
Keywords: periodic table,chemistry,elements,science
Author: Lukasz Mentel
Author-email: lmmentel@gmail.com
Maintainer: Lukasz Mentel
Maintainer-email: lmmentel@gmail.com
Requires-Python: >=3.9,<3.14
Classifier: Development Status :: 5 - Production/Stable
Classifier: Intended Audience :: Education
Classifier: Intended Audience :: Science/Research
Classifier: License :: OSI Approved :: MIT License
Classifier: Natural Language :: English
Classifier: Operating System :: OS Independent
Classifier: Programming Language :: Python :: 3
Classifier: Programming Language :: Python :: 3.9
Classifier: Programming Language :: Python :: 3.10
Classifier: Programming Language :: Python :: 3.11
Classifier: Programming Language :: Python :: 3.12
Classifier: Programming Language :: Python :: 3.13
Classifier: Programming Language :: Python :: 3 :: Only
Classifier: Programming Language :: Python :: 3.8
Classifier: Topic :: Scientific/Engineering :: Chemistry
Classifier: Topic :: Scientific/Engineering :: Physics
Classifier: Topic :: Software Development :: Libraries :: Python Modules
Requires-Dist: Pygments (>=2.11.2,<3.0.0)
Requires-Dist: SQLAlchemy (>=1.4.0)
Requires-Dist: colorama (>=0.4.6,<0.5.0)
Requires-Dist: deprecated (>=1.2.14,<2.0.0)
Requires-Dist: numpy (>=1.21,<2.0) ; python_version < "3.12"
Requires-Dist: numpy (>=2.0,<3.0) ; python_version >= "3.12"
Requires-Dist: pandas (>=1.0.0) ; python_version < "3.12"
Requires-Dist: pandas (>=2.1,<3.0) ; python_version >= "3.12" and python_version < "3.14"
Requires-Dist: pydantic (>=2.9.2,<3.0.0)
Requires-Dist: pyfiglet (>=0.8.post1,<0.9)
Project-URL: Documentation, https://mendeleev.readthedocs.io
Project-URL: Repository, https://github.com/lmmentel/mendeleev
